tickcounter/__init__.py
tickcounter/config.py
tickcounter/findings/__init__.py
tickcounter/findings/anova_findings.py
tickcounter/findings/chi_squared_findings.py
tickcounter/findings/dependence_findings.py
tickcounter/findings/findings.py
tickcounter/findings/findings_list.py
tickcounter/findings/t_test_findings.py
tickcounter/findings/test_result.py
tickcounter/plot/__init__.py
tickcounter/plot/plot.py
tickcounter/questionnaire/__init__.py
tickcounter/questionnaire/description.py
tickcounter/questionnaire/encoder.py
tickcounter/questionnaire/generate_json_encoding.py
tickcounter/questionnaire/interval_label.py
tickcounter/questionnaire/jsonencoder.py
tickcounter/questionnaire/label.py
tickcounter/questionnaire/multiencoder.py
tickcounter/questionnaire/quartile_label.py
tickcounter/questionnaire/questionnaire.py
tickcounter/questionnaire/scoring.py
tickcounter/statistics/__init__.py
tickcounter/statistics/statistics.py
tickcounter/survey/__init__.py
tickcounter/survey/survey.py
tickcounter/util/__init__.py
tickcounter/util/util.py
tickcounter-0.2.3.dist-info/LICENSE
tickcounter-0.2.3.dist-info/WHEEL
tickcounter-0.2.3.dist-info/METADATA
tickcounter-0.2.3.dist-info/RECORD
