Metadata-Version: 2.1
Name: tickcounter
Version: 0.2.3
Summary: A library for processing survey data
License: MIT
Author: Ong Eng Kheng
Requires-Python: >=3.7.1
Classifier: License :: OSI Approved :: MIT License
Classifier: Programming Language :: Python :: 3
Classifier: Programming Language :: Python :: 3.10
Classifier: Programming Language :: Python :: 3.8
Classifier: Programming Language :: Python :: 3.9
Requires-Dist: matplotlib (>=3.2.2)
Requires-Dist: pandas (>=1.3.5)
Requires-Dist: pyyaml (>=6.0)
Requires-Dist: scipy (>=1.4.1)
Requires-Dist: seaborn (>=0.11.2)
